MANIFEST.in
README.md
setup.py
texturizer/__init__.py
texturizer/__main__.py
texturizer/comparison.py
texturizer/config.py
texturizer/embedding.py
texturizer/emoticons.py
texturizer/featurize.py
texturizer/literacy.py
texturizer/pipeline.py
texturizer/pos.py
texturizer/process.py
texturizer/profanity.py
texturizer/reason.py
texturizer/rhetoric.py
texturizer/scarcity.py
texturizer/sentiment.py
texturizer/simple.py
texturizer/structure.py
texturizer/texturizer.py
texturizer/topics.py
texturizer/traits.py
texturizer.egg-info/PKG-INFO
texturizer.egg-info/SOURCES.txt
texturizer.egg-info/dependency_links.txt
texturizer.egg-info/entry_points.txt
texturizer.egg-info/requires.txt
texturizer.egg-info/top_level.txt
texturizer/data/arts.dat
texturizer/data/authority.dat
texturizer/data/cliches.dat
texturizer/data/conclusions.dat
texturizer/data/crime.dat
texturizer/data/culture.dat
texturizer/data/economics.dat
texturizer/data/education.dat
texturizer/data/emoticons-cheeky.dat
texturizer/data/emoticons-cry.dat
texturizer/data/emoticons-happy-cry.dat
texturizer/data/emoticons-kiss.dat
texturizer/data/emoticons-laugh.dat
texturizer/data/emoticons-sad.dat
texturizer/data/emoticons-sceptical.dat
texturizer/data/emoticons-shock.dat
texturizer/data/emoticons-smile.dat
texturizer/data/emoticons-wink.dat
texturizer/data/emoticons.dat
texturizer/data/ethnicity.dat
texturizer/data/explain.dat
texturizer/data/family.dat
texturizer/data/fashion.dat
texturizer/data/food.dat
texturizer/data/health.dat
texturizer/data/jargon.dat
texturizer/data/love.dat
texturizer/data/misspelling.dat
texturizer/data/negative-emoticons.dat
texturizer/data/negative-words.dat
texturizer/data/negative.dat
texturizer/data/nuance.dat
texturizer/data/politics.dat
texturizer/data/positive-emoticons.dat
texturizer/data/positive-words.dat
texturizer/data/positive.dat
texturizer/data/premises.dat
texturizer/data/reasoning.dat
texturizer/data/religion.dat
texturizer/data/scarcity.dat
texturizer/data/science.dat
texturizer/data/sex.dat
texturizer/data/sports.dat
texturizer/data/stop-words.dat
texturizer/data/technology.dat
texturizer/data/travel.dat