Metadata-Version: 2.1
Name: texturizer
Version: 0.1.9
Summary: Python command line application to add text features to a CSV or TSV dataset.
Home-page: http://john-hawkins.github.io
Author: John Hawkins
Author-email: johnc@getting-data-science-done.com
License: MIT
Project-URL: Documentation, http://texturizer.readthedocs.io
Project-URL: Source, https://github.com/john-hawkins/texturizer
Project-URL: Tracker, https://github.com/john-hawkins/texturizer/issues
Platform: UNKNOWN
